<?xml version="1.0" encoding="UTF-8"?>
<navigaters>
	<navigater>
		<title>首页</title>
		<action>index</action>
		<method>index</method>
		<img>fa fa-home</img>
		<desc>后台管理首页</desc>
	</navigater>
	<navigater>
		<title>用户管理</title>
		<action></action>
		<method></method>
		<img>fa fa-user</img>
		<desc>用户管理</desc>
		<navigaters>
			<navigater>
				<title>用户列表</title>
				<action>user</action>
				<method>list</method>
				<img>fa fa-long-arrow-right</img>
				<desc>用户信息管理</desc>
			</navigater>
			<navigater>
				<title>群组列表</title>
				<action>group</action>
				<method>list</method>
				<img>fa fa-long-arrow-right</img>
				<desc>群组管理</desc>
			</navigater>
			<navigater>
				<title>禁言设置</title>
				<action>forbid</action>
				<method>list</method>
				<img>fa fa-microphone-slash</img>
				<desc>禁言设置</desc>
			</navigater>
		</navigaters>
	</navigater>
	<navigater>
		<title>卡单管理</title>
		<action></action>
		<method></method>
		<img>fa fa-camera-retro</img>
		<desc>卡单管理</desc>
		<navigaters>
			<navigater>
				<title>卡单查看</title>
				<action>kadan</action>
				<method>list</method>
				<img>fa fa-info</img>
				<desc>卡单查看</desc>
			</navigater>
			<navigater>
				<title>新增卡单</title>
				<action>kadan</action>
				<method>add</method>
				<img>fa fa-tag</img>
				<desc>话题管理DESC</desc>
			</navigater>
		</navigaters>
	</navigater>
	<navigater>
		<title>通用设置</title>
		<action></action>
		<method></method>
		<img>fa fa-cogs</img>
		<desc>通用设置</desc>
		<navigaters>
			<navigater>
				<title>系统设置</title>
				<action>siteconfig</action>
				<method>list</method>
				<img>fa fa-cogs</img>
				<desc>系统基本信息配置</desc>
			</navigater>
			<navigater>
				<title>管理账户</title>
				<action>manage</action>
				<method>list</method>
				<img>fa fa-user</img>
				<desc>系统管理账户设置</desc>
			</navigater>
			<navigater>
				<title>操作日志</title>
				<action>manage</action>
				<method>log</method>
				<img>fa fa-long-arrow-right</img>
				<desc>系统管理账户操作日志</desc>
			</navigater>
		</navigaters>
	</navigater>
</navigaters>